npfastsortcpp/LICENSE
npfastsortcpp/README.MD
npfastsortcpp/__init__.py
npfastsortcpp/requirements.txt
npfastsortcpp/thirdparty.json
npfastsortcpp-0.10.dist-info/LICENSE.rst
npfastsortcpp-0.10.dist-info/METADATA
npfastsortcpp-0.10.dist-info/WHEEL
npfastsortcpp-0.10.dist-info/top_level.txt
npfastsortcpp-0.10.dist-info/RECORD
